z_eveng/__init__.py
z_eveng/eveng.py
z_eveng/eveng_res.py
z_eveng-0.0.1.6.dist-info/LICENSE
z_eveng-0.0.1.6.dist-info/METADATA
z_eveng-0.0.1.6.dist-info/WHEEL
z_eveng-0.0.1.6.dist-info/top_level.txt
z_eveng-0.0.1.6.dist-info/RECORD
