Metadata-Version: 2.1
Name: z-eveng
Version: 0.0.1.6
Author: Prajwal
Author-email: pkumarjha@zscaler.com
Classifier: Programming Language :: Python :: 3
Classifier: License :: OSI Approved :: MIT License
Classifier: Operating System :: OS Independent
Requires-Python: >=3.8
License-File: LICENSE
Requires-Dist: requests
